LICENSE
MANIFEST.in
README.rst
setup.cfg
setup.py
alis/__init__.py
alis/alis.py
alis.egg-info/PKG-INFO
alis.egg-info/SOURCES.txt
alis.egg-info/dependency_links.txt
alis.egg-info/requires.txt
alis.egg-info/top_level.txt
alis/lib/Call.py
alis/lib/Cognito.py
alis/lib/Pagination.py
alis/lib/Request.py
alis/lib/Util.py
alis/lib/__init__.py
alis/lib/apis.py