Metadata-Version: 2.1
Name: alis
Version: 0.0.4
Summary: ALIS API Python Client
Home-page: https://github.com/alisista/py-alis
Author: hoosan
Author-email: hoosanalis@gmail.com
License: MIT License
